{"publish_date":{"3700443":20140630,"3710343":20140630,"3700845":20140630,"3704023":20140630,"3703130":20140630,"3698090":20140630,"3707076":20140630,"3705587":20140630,"3698445":20140630,"3692508":20140630,"3705028":20140630,"3697457":20140630,"3702764":20140630,"3698191":20140630,"3696205":20140630,"3702568":20140630,"3703560":20140630,"3693272":20140630,"3704398":20140630},"url":{"3700443":"http:\/\/www.foxnews.com\/health\/2014\/06\/30\/could-ebola-spread-to-united-states\/&c=V0m45D_Fru87-vjGPN_6YWJZqzbeNRlj8QR1KzaY2RE&mkt=en-us","3710343":"http:\/\/www.bbc.co.uk\/news\/world-africa-28096916","3700845":"http:\/\/hosted.ap.org\/dynamic\/stories\/A\/AF_LIBERIA_EBOLA?SITE=MNWIN&SECTION=HOME&TEMPLATE=DEFAULT","3704023":"http:\/\/america.aljazeera.com\/articles\/2014\/6\/30\/ebola-liberia-africa.html","3703130":"http:\/\/www.brudirect.com\/0-health-lifestyle\/item\/5230-liberian-president-warns-against-hiding-ebola-patients\/RK=0","3698090":"http:\/\/uk.reuters.com\/article\/2014\/06\/27\/us-health-ebola-who-idUKKBN0F20TJ20140627","3707076":"http:\/\/vaccinenewsdaily.com\/medical_countermeasures\/331079-who-provides-expertise-to-combat-ebola-outbreak\/","3705587":"http:\/\/www.thenews.com.pk\/article-152156-Risk-of-Ebola-spread-in-west-Africa-WHO-warns","3698445":"http:\/\/www.premiumtimesng.com\/news\/foreign\/164120-182-die-from-ebola-in-guinea-says-health-officer.html","3692508":"http:\/\/www.delawareonline.com\/story\/news\/health\/2014\/06\/30\/ebola-outbreak-needs-urgent-action\/11785093\/?from=global&sessionKey=&autologin=","3705028":"http:\/\/www.washingtonpost.com\/opinions\/west-africa-cant-manage-the-ebola-outbreak\/2014\/06\/29\/07f4c354-fee9-11e3-b1f4-8e77c632c07b_story.html?wprss=rss_opinions","3697457":"http:\/\/www.post-gazette.com\/local\/2014\/06\/30\/U-S-groups-provide-relief-from-Ebola-in-W-Africa","3702764":"http:\/\/www.indiablooms.com\/ibns_new\/health-details\/H\/168\/ebola-outbreak-not-out-of-hand-un-health-agency-says-readying-response.html","3698191":"http:\/\/wesa.fm\/post\/brothers-brother-foundation-calls-donations-cope-west-africa-ebola-outbreak","3696205":"http:\/\/www.aljazeera.com\/news\/africa\/2014\/06\/liberia-warns-against-hiding-ebola-patients-201463014025366225.html","3702568":"http:\/\/www.wnd.com\/2014\/06\/tb-swine-flu-assaulting-border-agents-whos-next\/","3703560":"http:\/\/www.digitaljournal.com\/pr\/2025597&c=t7Vogo_RBIa_O4BT6mcqwpDxh7zLpyvGZNc30IiHcb0&mkt=en-us","3693272":"http:\/\/reliefweb.int\/report\/liberia\/unicef-liberia-ebola-virus-disease-sitrep-30-30-june-2014","3704398":"http:\/\/reliefweb.int\/report\/sierra-leone\/humanitarian-funding-analysis-ebola-outbreak-sierra-leone"},"topic":{"3700443":"ebola","3710343":"ebola","3700845":"ebola","3704023":"ebola","3703130":"ebola","3698090":"ebola","3707076":"ebola","3705587":"ebola","3698445":"ebola","3692508":"ebola","3705028":"ebola","3697457":"ebola","3702764":"ebola","3698191":"ebola","3696205":"ebola","3702568":"ebola","3703560":"ebola","3693272":"ebola","3704398":"ebola"},"model1_prediction":{"3700443":1,"3710343":1,"3700845":1,"3704023":1,"3703130":1,"3698090":1,"3707076":1,"3705587":1,"3698445":1,"3692508":1,"3705028":1,"3697457":1,"3702764":1,"3698191":1,"3696205":1,"3702568":1,"3703560":1,"3693272":1,"3704398":1},"model1_prediction_prob":{"3700443":0.999954596,"3710343":0.9999478148,"3700845":0.9998068467,"3704023":0.9996727542,"3703130":0.999599697,"3698090":0.9995388166,"3707076":0.9994628935,"3705587":0.9993828588,"3698445":0.9992804611,"3692508":0.9992165584,"3705028":0.9983995311,"3697457":0.9980356051,"3702764":0.9978761928,"3698191":0.9945982485,"3696205":0.9928118393,"3702568":0.981342388,"3703560":0.9726763584,"3693272":0.964340726,"3704398":0.9386624134},"title":{"3700443":"Could Ebola spread to the United States?","3710343":"Liberian president warns against hiding Ebola patients","3700845":"Winona Daily News","3704023":"Liberia vows prosecution for hiding Ebola patients amid regional epidemic","3703130":"Liberian President Warns Against Hiding Ebola Patients","3698090":"West African nations should be prepared for Ebola: WHO expert","3707076":"WHO provides expertise to combat ebola outbreak","3705587":"Risk of Ebola spread in west Africa, WHO warns","3698445":"182 die from ebola in Guinea, says health officer","3692508":"Ebola outbreak needs urgent action","3705028":"West Africa can\u2019t manage the Ebola outbreak","3697457":"U.S. groups provide relief from Ebola in West Africa","3702764":"Ebola outbreak 'not out of hand', UN health agency says readying response","3698191":"Brother's Brother Foundation Calls for Donations to Cope With West Africa Ebola Outbreak","3696205":"Liberia warns against hiding Ebola patients","3702568":"TB, swine flu assaulting border agents","3703560":"Samaritan's Purse sending Canadian medical specialists to Liberia to fight deadly Ebola virus","3693272":"UNICEF-Liberia Ebola Virus Disease: SitRep #30, 30 June 2014 - Liberia","3704398":"Humanitarian funding analysis: Ebola outbreak in Sierra Leone - Sierra Leone"}}