{"publish_date":{"10388223":20150228,"10411423":20150228},"url":{"10388223":"http:\/\/www.newindianexpress.com\/cities\/chennai\/Pay-up-if-Hosp-Found-Guilty\/2015\/02\/28\/article2690511.ece","10411423":"http:\/\/timesofindia.indiatimes.com\/city\/chennai\/Kidney-patients-get-hepatitis-C-at-hospital-HC-seeks-answers\/articleshow\/46403483.cms"},"topic":{"10388223":"hepat","10411423":"hepat"},"model1_prediction":{"10388223":1,"10411423":1},"model1_prediction_prob":{"10388223":0.5722757839,"10411423":0.5650853375},"title":{"10388223":"Pay up if Hosp Found Guilty","10411423":"Kidney patients get hepatitis C at hospital, HC seeks answers"}}