{"publish_date":{"15649573":20150723,"15631671":20150723,"15604795":20150723,"15608794":20150723,"15606655":20150723,"15605203":20150723,"15613108":20150723},"url":{"15649573":"http:\/\/scopeblog.stanford.edu\/category\/aging\/","15631671":"http:\/\/www.cidrap.umn.edu\/news-perspective\/2015\/07\/barda-recent-universal-flu-vaccine-proposals-fell-short","15604795":"http:\/\/chapelboro.com\/news\/state-news\/nc-officials-expect-to-see-more-cases-of-canine-influenza\/","15608794":"http:\/\/investmentwatchblog.com\/italian-court-rules-mercury-and-aluminum-in-vaccines-cause-autism-us-media-continues-total-blackout-of-medical-truth\/","15606655":"http:\/\/en.yibada.com\/articles\/47784\/20150723\/bird-flu-vaccine-100-effective-chickens-undergoing-turkey-testing-report.htm","15605203":"http:\/\/columbustelegram.com\/news\/state-and-regional\/nebraska-officials-lift-bird-flu-quarantine\/article_d2d476d1-e782-5272-a89b-df0d4bf3ea1d.html","15613108":"http:\/\/www.thepoultrysite.com\/poultrynews\/35475\/african-poultry-wrap-disease-pressures-poultry-price-fluctuations\/"},"topic":{"15649573":"influ","15631671":"influ","15604795":"influ","15608794":"influ","15606655":"influ","15605203":"influ","15613108":"influ"},"model1_prediction":{"15649573":1,"15631671":1,"15604795":1,"15608794":1,"15606655":1,"15605203":1,"15613108":1},"model1_prediction_prob":{"15649573":0.9479092829,"15631671":0.9088652964,"15604795":0.7799879809,"15608794":0.703555581,"15606655":0.6909460356,"15605203":0.5822724278,"15613108":0.5089999827},"title":{"15649573":"Scope Blog","15631671":"BARDA: Recent 'universal' flu vaccine proposals fell short","15604795":"NC Officials Expect To See More Cases of Canine Influenza","15608794":"Italian court rules mercury and aluminum in vaccines cause autism","15606655":"Bird Flu Vaccine 100% Effective On Chickens, Undergoing Turkey Testing","15605203":"Nebraska officials lift bird flu quarantine","15613108":"African Poultry Wrap: Disease Pressures; Poultry Price Fluctuations"}}