{"publish_date":{"819459":20140217,"821668":20140217},"url":{"819459":"http:\/\/gulfnews.com\/news\/world\/other-world\/27-countries-launch-effort-to-fight-outbreaks-1.1291869","821668":"http:\/\/reliefweb.int\/map\/namibia\/southern-africa-weekly-report-11-17-february-2014"},"topic":{"819459":"chole","821668":"chole"},"model1_prediction":{"819459":1,"821668":1},"model1_prediction_prob":{"819459":0.9125970628,"821668":0.8385026351},"title":{"819459":"27 countries launch effort to fight outbreaks","821668":"Southern Africa: Weekly Report (11 to 17 February 2014) - Namibia"}}