{"publish_date":{"13079470":20150515,"13102782":20150515,"13079097":20150515,"13106414":20150515,"13070008":20150515,"13075538":20150515,"13086467":20150515,"13072833":20150515},"url":{"13079470":"https:\/\/www.einnews.com\/pr_news\/265664226\/rapidly-growing-outbreak-of-meningococcal-disease-in-niger","13102782":"http:\/\/www.who.int\/csr\/don\/15-may-2015-niger\/en\/","13079097":"http:\/\/reliefweb.int\/report\/niger\/meningitis-niger-100-people-hospitalised-critical-condition-every-day-niamey","13106414":"http:\/\/www.news.va\/en\/news\/africaniger-meningitis-in-niger-100-people-hospita","13070008":"http:\/\/www.newsletter.co.uk\/news\/business\/potentially-deadly-bacteria-at-harland-and-wolff-1-6747531","13075538":"http:\/\/www.irishexaminer.com\/breakingnews\/ireland\/belfast-shipyard-struck-by-bacterial-outbreak-677365.html","13086467":"http:\/\/www.belfastlive.co.uk\/news\/health\/bacterial-infection-could-cause-deadly-9266117","13072833":"http:\/\/www.independent.ie\/irish-news\/news\/fears-of-spread-of-deadly-illnesses-as-bacterial-infection-breaks-out-at-shipyard-31226250.html"},"topic":{"13079470":"menin","13102782":"menin","13079097":"menin","13106414":"menin","13070008":"menin","13075538":"menin","13086467":"menin","13072833":"menin"},"model1_prediction":{"13079470":1,"13102782":1,"13079097":1,"13106414":1,"13070008":1,"13075538":1,"13086467":1,"13072833":1},"model1_prediction_prob":{"13079470":0.9988751552,"13102782":0.99876691,"13079097":0.9956929077,"13106414":0.962355649,"13070008":0.8690266837,"13075538":0.8401690963,"13086467":0.7163240741,"13072833":0.7040852119},"title":{"13079470":"Rapidly growing outbreak of meningococcal disease in Niger","13102782":"Rapidly growing outbreak of meningococcal disease in Niger","13079097":"Meningitis in Niger: 100 people hospitalised in critical condition every day in Niamey - Niger","13106414":"Meningitis in Niger: 100 people hospitalized every day in Niamey","13070008":"Potentially-deadly bacteria at Harland and Wolff","13075538":"Belfast shipyard struck by bacterial outbreak","13086467":"Employees offered vaccination after bacterial infection which could cause deadly illnesses breaks out at Belfast's Harland and Wolff","13072833":"Fears of spread of deadly illnesses as bacterial infection breaks out at shipyard"}}