{"publish_date":{"3796744":20140704,"3804203":20140704,"3792394":20140704,"3792397":20140704,"3800420":20140704,"3794162":20140704,"3800189":20140704,"3804710":20140704,"3806540":20140704,"3808245":20140704},"url":{"3796744":"http:\/\/www.bostonglobe.com\/metro\/2014\/07\/03\/chikungunya-cases-reported-boston-among-travelers-caribbean\/RQGxIM0j4ID4AFcDupiFOP\/story.html","3804203":"http:\/\/www.observer-reporter.com\/article\/20140704\/NEWS01\/140709776\/RK=0","3792394":"http:\/\/guardianlv.com\/2014\/07\/chikungunya-mosquito-virus-getting-more-attention-in-the-u-s\/","3792397":"http:\/\/guardianlv.com\/2014\/07\/caribbean-ravaged-due-to-rampancy-of-virus\/","3800420":"http:\/\/www.hngn.com\/articles\/35294\/20140704\/chikungunya-virus-recorded-in-boston-after-travelers-return-from-the-caribbean.htm&c=Vj_prVnSGDtAKKRBMo1TC3GyAGgMepPzuEE_KyceDuk&mkt=en-us","3794162":"http:\/\/reliefweb.int\/report\/dominican-republic\/heavy-rainy-season-latin-america-and-caribbean-could-cause-significant","3800189":"http:\/\/www.guardian.co.tt\/news\/2014-07-04\/chikungunya-virus-warning-tt","3804710":"http:\/\/www.post-gazette.com\/local\/region\/2014\/07\/04\/Mosquito-virus-stings-state-with-health-alert\/stories\/201407020200","3806540":"http:\/\/www.theblaze.com\/stories\/2014\/07\/04\/this-breed-of-mosquito-is-invading-the-u-s-and-it-could-carry-a-terrifying-disease\/","3808245":"http:\/\/www.turnto10.com\/story\/25936421\/health-check-special-report-chikungunya"},"topic":{"3796744":"chiku","3804203":"chiku","3792394":"chiku","3792397":"chiku","3800420":"chiku","3794162":"chiku","3800189":"chiku","3804710":"chiku","3806540":"chiku","3808245":"chiku"},"model1_prediction":{"3796744":1,"3804203":1,"3792394":1,"3792397":1,"3800420":1,"3794162":1,"3800189":1,"3804710":1,"3806540":1,"3808245":1},"model1_prediction_prob":{"3796744":0.999097238,"3804203":0.9983702497,"3792394":0.997350455,"3792397":0.9960412473,"3800420":0.9959068793,"3794162":0.992366519,"3800189":0.9625772899,"3804710":0.9502552463,"3806540":0.9331092074,"3808245":0.9257438381},"title":{"3796744":"4 chikungunya cases reported in Boston among travelers to Caribbean","3804203":"Caribbean mosquito-borne virus making its way to U.S.","3792394":"Chikungunya Mosquito Virus Getting More Attention in the U.S.","3792397":"Caribbean Ravaged Due to Rampancy of Virus","3800420":"Chikungunya Virus Recorded in Boston After Travelers Return From the Caribbean","3794162":"Heavy rainy season in Latin America and the Caribbean could cause significant outbreaks - Dominican Republic","3800189":"Chikungunya virus warning for T&T","3804710":"State issues health alert on emerging mosquito virus","3806540":"This Breed of Mosquito Is Invading the U.S. \u2014 And It Could Carry a Terrifying Disease","3808245":"Health Check Special Report: Chikungunya"}}