{"publish_date":{"9316947":20150126,"9331283":20150126,"9331355":20150126,"9315151":20150126,"9319686":20150126,"9317336":20150126,"9339363":20150126,"9343511":20150126,"9342727":20150126,"9322439":20150126,"9329782":20150126,"9345429":20150126,"9326169":20150126,"9329127":20150126,"9318953":20150126,"9337091":20150126,"9323563":20150126,"9320991":20150126,"9325874":20150126,"9342611":20150126,"9321620":20150126,"9320928":20150126,"9343513":20150126,"9329447":20150126,"9334769":20150126,"9338232":20150126,"9338300":20150126,"9339027":20150126,"9321602":20150126,"9335230":20150126,"9329400":20150126,"9332737":20150126},"url":{"9316947":"http:\/\/finance.yahoo.com\/news\/public-health-notice-h7n9-avian-232200131.html","9331283":"http:\/\/www.newswire.ca\/en\/story\/1477627\/public-health-notice-update-h7n9-avian-flu","9331355":"http:\/\/www.myfoxdc.com\/story\/27939428\/5-year-old-las-vegas-girl-dies-from-flu-despite-receiving-vaccination","9315151":"http:\/\/bc.ctvnews.ca\/b-c-woman-diagnosed-with-first-h7n9-flu-case-in-north-america-1.2206525","9319686":"http:\/\/outbreaknewstoday.com\/idaho-reports-13-flu-deaths-in-past-two-weeks-93419\/","9317336":"http:\/\/globalnews.ca\/news\/1793690\/north-americas-first-human-case-of-h7n9-avian-flu-confirmed-in-b-c\/","9339363":"http:\/\/www.thespec.com\/news-story\/5276972-canada-finds-case-of-h7n9-bird-flu-in-traveller-first-in-north-america\/","9343511":"http:\/\/www.castanet.net\/news\/Canada\/131495\/More-on-Canada-s-first-H7N9-case","9342727":"http:\/\/www.timescolonist.com\/opinion\/blogs\/h7n9-bird-flu-diagnosed-in-b-c-traveller-first-in-north-america-1.1742661","9322439":"http:\/\/www.today.com\/health\/how-doctors-nurses-avoid-catching-flu-colds-2D80448453","9329782":"http:\/\/www.ctvnews.ca\/health\/north-america-s-first-human-case-of-h7n9-virus-confirmed-in-b-c-1.2206474","9345429":"http:\/\/www.ctvnews.ca\/health\/north-america-s-first-human-case-of-h7n9-bird-flu-virus-confirmed-in-b-c-1.2206474","9326169":"http:\/\/www.transylvaniatimes.com\/story\/2015\/01\/26\/news\/mission-institutes-visitor-limitation-policy-brevard-nc\/21360.html","9329127":"http:\/\/www.scmp.com\/news\/world\/article\/1693111\/vancouver-woman-diagnosed-h7n9-bird-flu-after-flight-hong-kong","9318953":"http:\/\/news.gc.ca\/web\/article-en.do?mthd=index&crtr.page=1&nid=925749&_ga=1.250200270.952491432.1415654405","9337091":"http:\/\/www.ctvnews.ca\/health\/plague-is-endemic-in-madagascar-who-chief-1.2205946","9323563":"http:\/\/www.newswire.ca\/en\/story\/1477505\/government-of-canada-and-british-columbia-confirm-case-of-h7n9-avian-influenza-in-canada","9320991":"http:\/\/www.theprovince.com\/health\/traveller+diagnosed+with+h7n9+bird+after+returning+from+china\/10761534\/story.html","9325874":"http:\/\/www.calgaryherald.com\/news\/metro\/traveller+diagnosed+with+H7N9+bird+after+returning+from+China+first\/10761534\/story.html","9342611":"http:\/\/vancouver.24hrs.ca\/2015\/01\/26\/vancouver-nurse-says-flu-policy-leading-to-unhealthy-work-environment","9321620":"http:\/\/www.elkvalleytimes.com\/?p=35739","9320928":"http:\/\/www.capitalpress.com\/Livestock\/20150126\/h5n1-bird-flu-found-in-washington-little-human-health-risk-since","9343513":"http:\/\/www.turlockjournal.com\/section\/12\/article\/28457\/","9329447":"http:\/\/www.wrex.com\/story\/27944926\/2015\/01\/26\/rockford-hospitals-lift-visitor-age-restrictions","9334769":"http:\/\/www.news1130.com\/2015\/01\/26\/british-columbian-diagnosed-with-first-human-case-of-avian-flu-in-north-america\/","9338232":"http:\/\/www.cidrap.umn.edu\/news-perspective\/2015\/01\/h5n8-virus-surfaces-california-turkey-farm","9338300":"http:\/\/www.abqjournal.com\/531156\/opinion\/treatment-options-few-for-lung-illness.html","9339027":"http:\/\/www.globalresearch.ca\/centers-for-disease-controls-cdc-own-data-shows-links-between-vaccines-and-sudden-infant-death-syndrome-sids\/5426990","9321602":"http:\/\/www.princegeorgecitizen.com\/news\/national\/bird-flu-in-bc-first-case-in-north-america-1.1742871","9335230":"http:\/\/www.latimes.com\/local\/lanow\/la-me-ln-avian-flu-central-valley-20150125-story.html","9329400":"http:\/\/www.inforum.com\/variety\/3664598-anatomy-common-cold-doctors-break-down-whats-going-and-what-we-should-do","9332737":"http:\/\/wuis.org\/post\/poultry-industry-warily-watches-bird-flu-outbreak"},"topic":{"9316947":"influ","9331283":"influ","9331355":"influ","9315151":"influ","9319686":"influ","9317336":"influ","9339363":"influ","9343511":"influ","9342727":"influ","9322439":"influ","9329782":"influ","9345429":"influ","9326169":"influ","9329127":"influ","9318953":"influ","9337091":"influ","9323563":"influ","9320991":"influ","9325874":"influ","9342611":"influ","9321620":"influ","9320928":"influ","9343513":"influ","9329447":"influ","9334769":"influ","9338232":"influ","9338300":"influ","9339027":"influ","9321602":"influ","9335230":"influ","9329400":"influ","9332737":"influ"},"model1_prediction":{"9316947":1,"9331283":1,"9331355":1,"9315151":1,"9319686":1,"9317336":1,"9339363":1,"9343511":1,"9342727":1,"9322439":1,"9329782":1,"9345429":1,"9326169":1,"9329127":1,"9318953":1,"9337091":1,"9323563":1,"9320991":1,"9325874":1,"9342611":1,"9321620":1,"9320928":1,"9343513":1,"9329447":1,"9334769":1,"9338232":1,"9338300":1,"9339027":1,"9321602":1,"9335230":1,"9329400":1,"9332737":1},"model1_prediction_prob":{"9316947":0.9970798406,"9331283":0.9969762807,"9331355":0.9965263064,"9315151":0.9965139236,"9319686":0.9952756234,"9317336":0.9951721398,"9339363":0.9932759954,"9343511":0.9930132169,"9342727":0.992850772,"9322439":0.9910962396,"9329782":0.9885548354,"9345429":0.9885548354,"9326169":0.9798208766,"9329127":0.9721575744,"9318953":0.9692603238,"9337091":0.9665750952,"9323563":0.9657940056,"9320991":0.9654520797,"9325874":0.9582851332,"9342611":0.9534197488,"9321620":0.9514271405,"9320928":0.9437875689,"9343513":0.9431126798,"9329447":0.9275793844,"9334769":0.8380331952,"9338232":0.8298744095,"9338300":0.814892289,"9339027":0.7946456723,"9321602":0.7260258223,"9335230":0.7143920503,"9329400":0.6907473257,"9332737":0.5913181063},"title":{"9316947":"Public Health Notice Update: H7N9 avian flu","9331283":"Public Health Notice Update: H7N9 avian flu -- OTTAWA, Jan. 26, 2015","9331355":"5-year-old Las Vegas girl dies from flu despite receiving vaccination - Story","9315151":"B.C. woman diagnosed with first H7N9 flu case in North America","9319686":"Idaho reports 13 flu deaths in past two weeks","9317336":"North America\u2019s first human case of H7N9 avian flu confirmed in B.C.","9339363":"Canada finds case of H7N9 bird flu in traveller; first in North America","9343511":"More on Canada's first H7N9 case","9342727":"H7N9 bird flu diagnosed in B.C. traveller; first in North America","9322439":"How doctors and nurses avoid catching the flu and colds","9329782":"North America's first human case of H7N9 bird flu virus confirmed in B.C.","9345429":"North America's first human case of H7N9 bird flu virus confirmed in B.C.","9326169":"Mission Institutes Visitor Limitation Policy-Brevard NC","9329127":"Woman flying from Hong Kong to Vancouver becomes first human bird flu case in North America","9318953":"Government of Canada and British Columbia confirm case of H7N9 avian influenza in Canada","9337091":"WHO chief Margaret Chan warns of 'alarming' plague outbreak in Madagascar","9323563":"Government of Canada and British Columbia confirm case of H7N9 avian influenza in Canada -- OTTAWA, Jan. 26, 2015","9320991":"B.C. woman tests positive for H7N9 bird flu after trip to China","9325874":"B.C. woman tests positive for H7N9 bird flu after trip to China","9342611":"Nurse says flu policy makes unhealthy workplace","9321620":"Fayetteville, Breaking News, Newspaper, Lincoln County, Park City, Flintville, Petersburg, Redstone, Huntsville, Hazel Green, Goodman, Frito-Lay, Stonebridge, Elk River, Distillery, Motlow, Fair in Te","9320928":"H5N1 bird flu found in Washington; little human health risk since","9343513":"Avian flu found in Stanislaus County turkey flock","9329447":"Rockford hospitals lift visitor age restrictions","9334769":"BC woman diagnosed with first human case of H7N9 avian flu in North America","9338232":"H5N8 virus surfaces on California turkey farm","9338300":"Treatment options few for lung illness","9339027":"Centers for Disease Control\u2019s (CDC) Own Data Shows Links Between Vaccines and Sudden Infant Death Syndrome (SIDS)","9321602":"Bird flu in BC first case in North America","9335230":"Avian flu detected at Central Valley farm","9329400":"Anatomy of the common cold: Doctors break down what's going on and what we should do","9332737":"Poultry Industry Warily Watches Bird Flu Outbreak"}}