{"publish_date":{"13836627":20150606,"13821428":20150606,"13821429":20150606,"13821430":20150606,"13821433":20150606,"13828746":20150606},"url":{"13836627":"http:\/\/www.bordermail.com.au\/story\/3128223\/flu-cases-tracking-at-record-levels\/?cs=4067","13821428":"http:\/\/590kid.com\/2015\/06\/05\/aurora-shooting-trial-10-new-things-from-james-holmes-psychiatric-evaluation-interviews\/","13821429":"http:\/\/590kid.com\/2015\/06\/05\/canadian-teen-makes-graduation-dress-out-of-homework-to-support-malala\/","13821430":"http:\/\/590kid.com\/2015\/06\/05\/british-counter-terrorism-police-turn-to-youtube-star-humza-ashrad-to-prevent-youth-radicalization\/","13821433":"http:\/\/590kid.com\/2015\/06\/05\/saddam-hussein-aide-tariq-aziz-dies-from-apparent-heart-attack\/","13828746":"http:\/\/www.smn-news.com\/st-maarten-st-martin-news\/18872-medical-officer-of-health-and-director-of-primary-healthcare-dr-kiran-kumar-retires.html"},"topic":{"13836627":"influ","13821428":"influ","13821429":"influ","13821430":"influ","13821433":"influ","13828746":"influ"},"model1_prediction":{"13836627":1,"13821428":1,"13821429":1,"13821430":1,"13821433":1,"13828746":1},"model1_prediction_prob":{"13836627":0.9933645501,"13821428":0.7511885505,"13821429":0.7511885505,"13821430":0.7511885505,"13821433":0.7511885505,"13828746":0.5169940984},"title":{"13836627":"Flu cases tracking at record levels","13821428":"June 5, 2015 Archives","13821429":"June 5, 2015 Archives","13821430":"June 5, 2015 Archives","13821433":"June 5, 2015 Archives","13828746":"Medical Officer of Health and Director of Primary Healthcare, Dr Kiran Kumar retires"}}