{"publish_date":{"7296583":20141111,"7303784":20141111,"7276565":20141111},"url":{"7296583":"http:\/\/www.wyff4.com\/spartanburg-regional-healthcare-system\/monitoring-enterovirus-in-the-upstate\/29645860","7303784":"http:\/\/www.poughkeepsiejournal.com\/story\/news\/local\/2014\/11\/10\/families-fight-flu\/18829731\/","7276565":"http:\/\/info.scoop.co.nz\/Northland_District_Health_Board"},"topic":{"7296583":"influ","7303784":"influ","7276565":"influ"},"model1_prediction":{"7296583":1,"7303784":1,"7276565":1},"model1_prediction_prob":{"7296583":0.9965156804,"7303784":0.9925780369,"7276565":0.5094503486},"title":{"7296583":"Spartanburg Regional Healthcare System - WYFF Home","7303784":"After death of daughter, Scarsdale parents urge flu vaccine","7276565":"Northland District Health Board"}}