{"publish_date":{"19131415":20151019,"19114448":20151019,"19116619":20151019,"19125212":20151019,"19140142":20151019,"19124048":20151019,"19152255":20151019},"url":{"19131415":"http:\/\/www.freepressjournal.in\/special-dengue-ward-in-ayurveda-hospital-waits-for-patients\/","19114448":"http:\/\/indianexpress.com\/article\/cities\/pune\/spike-in-viral-fever-cases-in-pune-doctors-say-is-self-limiting\/","19116619":"http:\/\/nation.com.pk\/islamabad\/19-Oct-2015\/dengue-outbreak-feared-in-wah","19125212":"http:\/\/www.readingeagle.com\/ap\/article\/indian-capital-struggles-to-control-dengue-fever-outbreak","19140142":"http:\/\/www.nyoooz.com\/lucknow\/234996\/15-dengue-cases-in-four-days","19124048":"http:\/\/tribune.com.pk\/story\/975726\/a-stinging-blow-dengue-cases-rise-to-27-in-swat\/","19152255":"http:\/\/www.thestar.com.my\/Metro\/Community\/2015\/10\/19\/All-abuzz-with-antidengue-info-Roadshow-aims-to-reinforce-message-to-prevent-disease\/"},"topic":{"19131415":"dengu","19114448":"dengu","19116619":"dengu","19125212":"dengu","19140142":"dengu","19124048":"dengu","19152255":"dengu"},"model1_prediction":{"19131415":1,"19114448":1,"19116619":1,"19125212":1,"19140142":1,"19124048":1,"19152255":1},"model1_prediction_prob":{"19131415":0.996370567,"19114448":0.9884802181,"19116619":0.9790393403,"19125212":0.9571945691,"19140142":0.8826080105,"19124048":0.8705217398,"19152255":0.7281814369},"title":{"19131415":"Special Dengue Ward in Ayurveda hospital waits for patients","19114448":"Spike in viral fever cases in Pune, doctors say is \u2018self-limiting\u2019","19116619":"Dengue outbreak feared in Wah","19125212":"Indian capital struggles to control dengue fever outbreak","19140142":"15 dengue cases in four days","19124048":"A stinging blow : Dengue cases rise to 27 in Swat","19152255":"All abuzz with anti-dengue info - Community"}}