{"publish_date":{"7089559":20141104,"7085693":20141104,"7066688":20141104,"7083731":20141104,"7086614":20141104,"7090690":20141104,"7087031":20141104,"7082045":20141104,"7088868":20141104,"7074083":20141104},"url":{"7089559":"http:\/\/www.cidrap.umn.edu\/news-perspective\/2014\/11\/news-scan-nov-04-2014","7085693":"http:\/\/www.thehealthsite.com\/news\/dengue-update-bhopal-dengue-cases-cross-500\/","7066688":"http:\/\/timesofindia.indiatimes.com\/City\/Bhopal\/Bhopal-reports-500th-dengue-case-no-end-in-sight\/articleshow\/45031726.cms","7083731":"http:\/\/shanghaidaily.com\/article\/article_xinhua.aspx?id=250570","7086614":"http:\/\/www.todayonline.com\/singapore\/78-year-old-4th-person-die-dengue-year","7090690":"http:\/\/www.thesundaily.my\/news\/1216720","7087031":"http:\/\/indiatoday.intoday.in\/story\/dengue-vaccine-sanofi\/1\/399150.html","7082045":"http:\/\/www.thehindu.com\/business\/Industry\/worlds-first-dengue-vaccine-likely-by-2015-sanofi\/article6564318.ece","7088868":"http:\/\/www.indiatvnews.com\/news\/india\/world-s-st-dengue-vaccine-likely-by-sanofi-43904.html","7074083":"http:\/\/www.malaysiasun.com\/index.php\/sid\/227305425"},"topic":{"7089559":"dengu","7085693":"dengu","7066688":"dengu","7083731":"dengu","7086614":"dengu","7090690":"dengu","7087031":"dengu","7082045":"dengu","7088868":"dengu","7074083":"dengu"},"model1_prediction":{"7089559":1,"7085693":1,"7066688":1,"7083731":1,"7086614":1,"7090690":1,"7087031":1,"7082045":1,"7088868":1,"7074083":1},"model1_prediction_prob":{"7089559":0.9950542771,"7085693":0.9908170816,"7066688":0.9795425651,"7083731":0.9557174234,"7086614":0.9277025533,"7090690":0.8649365304,"7087031":0.8145010227,"7082045":0.7775601953,"7088868":0.7191579513,"7074083":0.5750369643},"title":{"7089559":"News Scan for Nov 04, 2014","7085693":"Read Health News & Articles at TheHealthSite.com","7066688":"Bhopal reports 500th dengue case, no end in sight","7083731":"New dengue vaccine tested in Brazil proven effective","7086614":"78-year-old is 4th person to die from dengue this year","7090690":"Crisis meeting following spike in dengue cases","7087031":"World's 1st dengue vaccine likely by 2015: Sanofi : World, News","7082045":"World\u2019s first dengue vaccine likely by 2015: Sanofi","7088868":"World's 1st dengue vaccine likely by 2015","7074083":"Dengue: Muhyiddin chairs National-Level Committee meeting"}}