{"hemmo": {"sample_sd": 0.0, "sample_mean": 0.0, "daily_article_count": 0, "30_day_error_count": 0, "threshold_warn": 0.0, "30_day_warn_count": 0, "daily_sd": 0, "threshold_error": 0.0}, "mersc": {"sample_sd": 0.66999170807472608, "sample_mean": 0.46666666666666667, "daily_article_count": 0, "30_day_error_count": 0, "threshold_warn": 1.8066500828161187, "30_day_warn_count": 0, "daily_sd": -0.69652603314699235, "threshold_error": 2.4766417908908451}, "influ": {"sample_sd": 0.52599112793531666, "sample_mean": 0.29999999999999999, "daily_article_count": 1, "30_day_error_count": 1, "threshold_warn": 1.3519822558706334, "30_day_warn_count": 0, "daily_sd": 1.3308209261014035, "threshold_error": 1.87797338380595}, "pertu": {"sample_sd": 0.0, "sample_mean": 0.0, "daily_article_count": 0, "30_day_error_count": 0, "threshold_warn": 0.0, "30_day_warn_count": 0, "daily_sd": 0, "threshold_error": 0.0}, "moldf": {"sample_sd": 0.0, "sample_mean": 0.0, "daily_article_count": 0, "30_day_error_count": 0, "threshold_warn": 0.0, "30_day_warn_count": 0, "daily_sd": 0, "threshold_error": 0.0}, "chole": {"sample_sd": 0.60461190490723515, "sample_mean": 0.36666666666666664, "daily_article_count": 0, "30_day_error_count": 1, "threshold_warn": 1.575890476481137, "30_day_warn_count": 0, "daily_sd": -0.60644963106196836, "threshold_error": 2.1805023813883722}, "hepat": {"sample_sd": 0.0, "sample_mean": 0.0, "daily_article_count": 0, "30_day_error_count": 0, "threshold_warn": 0.0, "30_day_warn_count": 0, "daily_sd": 0, "threshold_error": 0.0}, "chiku": {"sample_sd": 0.37267799624996495, "sample_mean": 0.16666666666666666, "daily_article_count": 0, "30_day_error_count": 1, "threshold_warn": 0.91202265916659653, "30_day_warn_count": 0, "daily_sd": -0.44721359549995793, "threshold_error": 1.2847006554165616}, "yello": {"sample_sd": 0.74833147735478822, "sample_mean": 0.20000000000000001, "daily_article_count": 0, "30_day_error_count": 1, "threshold_warn": 1.6966629547095764, "30_day_warn_count": 0, "daily_sd": -0.2672612419124244, "threshold_error": 2.4449944320643651}, "menin": {"sample_sd": 0.0, "sample_mean": 0.0, "daily_article_count": 0, "30_day_error_count": 2, "threshold_warn": 0.0, "30_day_warn_count": 0, "daily_sd": 0, "threshold_error": 0.0}, "plagu": {"sample_sd": 0.0, "sample_mean": 0.0, "daily_article_count": 0, "30_day_error_count": 0, "threshold_warn": 0.0, "30_day_warn_count": 0, "daily_sd": 0, "threshold_error": 0.0}, "westn": {"sample_sd": 0.30000000000000004, "sample_mean": 0.10000000000000001, "daily_article_count": 0, "30_day_error_count": 0, "threshold_warn": 0.70000000000000007, "30_day_warn_count": 0, "daily_sd": -0.33333333333333331, "threshold_error": 1.0000000000000002}, "swine": {"sample_sd": 0.67986926847903806, "sample_mean": 0.26666666666666666, "daily_article_count": 0, "30_day_error_count": 0, "threshold_warn": 1.6264052036247427, "30_day_warn_count": 0, "daily_sd": -0.39223227027636803, "threshold_error": 2.3062744721037807}, "measl": {"sample_sd": 0.0, "sample_mean": 0.0, "daily_article_count": 0, "30_day_error_count": 0, "threshold_warn": 0.0, "30_day_warn_count": 0, "daily_sd": 0, "threshold_error": 0.0}, "dengu": {"sample_sd": 0.90676470058236291, "sample_mean": 0.66666666666666663, "daily_article_count": 1, "30_day_error_count": 0, "threshold_warn": 2.4801960678313923, "30_day_warn_count": 0, "daily_sd": 0.36760731104690392, "threshold_error": 3.3869607684137555}, "ebola": {"sample_sd": 15.852830101348536, "sample_mean": 36.43333333333333, "daily_article_count": 26, "30_day_error_count": 4, "threshold_warn": 68.138993536030398, "30_day_warn_count": 0, "daily_sd": -0.65813695514505066, "threshold_error": 83.991823637378928}, "unkno": {"sample_sd": 2.4094720491334938, "sample_mean": 3.1666666666666665, "daily_article_count": 1, "30_day_error_count": 1, "threshold_warn": 7.9856107649336536, "30_day_warn_count": 0, "daily_sd": -0.89922880302589681, "threshold_error": 10.395082814067148}, "mumps": {"sample_sd": 0.0, "sample_mean": 0.0, "daily_article_count": 0, "30_day_error_count": 0, "threshold_warn": 0.0, "30_day_warn_count": 0, "daily_sd": 0, "threshold_error": 0.0}}