{"hemmo": {"sample_sd": 0.17950549357115012, "sample_mean": 0.033333333333333333, "daily_article_count": 0, "30_day_error_count": 1, "threshold_warn": 0.39234432047563356, "30_day_warn_count": 0, "daily_sd": -0.18569533817705189, "threshold_error": 0.5718498140467837}, "mersc": {"sample_sd": 0.24944382578492943, "sample_mean": 0.066666666666666666, "daily_article_count": 0, "30_day_error_count": 1, "threshold_warn": 0.56555431823652558, "30_day_warn_count": 0, "daily_sd": -0.2672612419124244, "threshold_error": 0.81499814402145498}, "influ": {"sample_sd": 0.24944382578492943, "sample_mean": 0.066666666666666666, "daily_article_count": 0, "30_day_error_count": 5, "threshold_warn": 0.56555431823652558, "30_day_warn_count": 0, "daily_sd": -0.2672612419124244, "threshold_error": 0.81499814402145498}, "pertu": {"sample_sd": 0.0, "sample_mean": 0.0, "daily_article_count": 0, "30_day_error_count": 0, "threshold_warn": 0.0, "30_day_warn_count": 0, "daily_sd": 0, "threshold_error": 0.0}, "moldf": {"sample_sd": 0.0, "sample_mean": 0.0, "daily_article_count": 0, "30_day_error_count": 0, "threshold_warn": 0.0, "30_day_warn_count": 0, "daily_sd": 0, "threshold_error": 0.0}, "chole": {"sample_sd": 0.77172246018601509, "sample_mean": 0.26666666666666666, "daily_article_count": 0, "30_day_error_count": 0, "threshold_warn": 1.8101115870386968, "30_day_warn_count": 0, "daily_sd": -0.345547370232544, "threshold_error": 2.5818340472247119}, "hepat": {"sample_sd": 0.17950549357115012, "sample_mean": 0.033333333333333333, "daily_article_count": 0, "30_day_error_count": 0, "threshold_warn": 0.39234432047563356, "30_day_warn_count": 0, "daily_sd": -0.18569533817705189, "threshold_error": 0.5718498140467837}, "chiku": {"sample_sd": 0.0, "sample_mean": 0.0, "daily_article_count": 0, "30_day_error_count": 0, "threshold_warn": 0.0, "30_day_warn_count": 0, "daily_sd": 0, "threshold_error": 0.0}, "yello": {"sample_sd": 0.0, "sample_mean": 0.0, "daily_article_count": 0, "30_day_error_count": 0, "threshold_warn": 0.0, "30_day_warn_count": 0, "daily_sd": 0, "threshold_error": 0.0}, "menin": {"sample_sd": 0.17950549357115014, "sample_mean": 0.033333333333333333, "daily_article_count": 0, "30_day_error_count": 1, "threshold_warn": 0.39234432047563361, "30_day_warn_count": 0, "daily_sd": -0.18569533817705186, "threshold_error": 0.5718498140467837}, "plagu": {"sample_sd": 0.0, "sample_mean": 0.0, "daily_article_count": 0, "30_day_error_count": 0, "threshold_warn": 0.0, "30_day_warn_count": 0, "daily_sd": 0, "threshold_error": 0.0}, "westn": {"sample_sd": 0.0, "sample_mean": 0.0, "daily_article_count": 0, "30_day_error_count": 0, "threshold_warn": 0.0, "30_day_warn_count": 0, "daily_sd": 0, "threshold_error": 0.0}, "swine": {"sample_sd": 0.37267799624996495, "sample_mean": 0.16666666666666666, "daily_article_count": 0, "30_day_error_count": 1, "threshold_warn": 0.91202265916659653, "30_day_warn_count": 0, "daily_sd": -0.44721359549995793, "threshold_error": 1.2847006554165616}, "measl": {"sample_sd": 0.0, "sample_mean": 0.0, "daily_article_count": 0, "30_day_error_count": 0, "threshold_warn": 0.0, "30_day_warn_count": 0, "daily_sd": 0, "threshold_error": 0.0}, "dengu": {"sample_sd": 1.3828312341794362, "sample_mean": 0.56666666666666665, "daily_article_count": 0, "30_day_error_count": 0, "threshold_warn": 3.3323291350255388, "30_day_warn_count": 0, "daily_sd": -0.40978729194161084, "threshold_error": 4.7151603692049751}, "ebola": {"sample_sd": 10.753242405071235, "sample_mean": 5.6333333333333337, "daily_article_count": 1, "30_day_error_count": 0, "threshold_warn": 27.139818143475804, "30_day_warn_count": 0, "daily_sd": -0.43087779097663148, "threshold_error": 37.893060548547041}, "unkno": {"sample_sd": 4.188476254359494, "sample_mean": 1.7, "daily_article_count": 0, "30_day_error_count": 0, "threshold_warn": 10.076952508718987, "30_day_warn_count": 0, "daily_sd": -0.40587552531319426, "threshold_error": 14.265428763078482}, "mumps": {"sample_sd": 0.0, "sample_mean": 0.0, "daily_article_count": 0, "30_day_error_count": 1, "threshold_warn": 0.0, "30_day_warn_count": 0, "daily_sd": 0, "threshold_error": 0.0}}