{"publish_date":{"133305":20140908,"133294":20140908,"133183":20140908,"133179":20140908,"133293":20140908,"133194":20140908},"url":{"133305":null,"133294":null,"133183":null,"133179":null,"133293":null,"133194":null},"topic":{"133305":"ebola","133294":"ebola","133183":"ebola","133179":"ebola","133293":"ebola","133194":"ebola"},"model1_prediction":{"133305":1,"133294":1,"133183":1,"133179":1,"133293":1,"133194":1},"model1_prediction_prob":{"133305":0.8783377419,"133294":0.8638291329,"133183":0.6150866358,"133179":0.612939163,"133293":0.5377750808,"133194":0.5081168809},"tweet_text":{"133305":"Early Epidemic Dynamics of the West African 2014 Ebola Outbreak: Estimates Derived with a Simple Two-Parameter Model http:\/\/t.co\/DYVtZPpRMe","133294":"RT: Studies that have detected Ebola virus using only immunofluorescent techniques \"totally unreliable\" h\/t http:\/\/\u2026","133183":"An Ebola vaccine, GlobalHealthSecurity at local health depts., and new ClimateChange challenges. HealthSecurity http:\/\/t.co\/H1JhGDbj22","133179":"RT: Ebola situation in Liberia: non-conventional interventions needed http:\/\/t.co\/n8TK0e6Pci","133293":"RT: Another Ebola patient coming to Atlanta hospital http:\/\/t.co\/J408VgCXdN","133194":"RT: Sierra Leone lockdown will not help halt Ebola: MSF http:\/\/t.co\/ckEP27syVH"}}