{"publish_date":{"26529":20150220,"26530":20150220},"url":{"26529":null,"26530":null},"topic":{"26529":"chole","26530":"chole"},"model1_prediction":{"26529":1,"26530":1},"model1_prediction_prob":{"26529":0.8964065757,"26530":0.8337937192},"tweet_text":{"26529":"RT: Southern Africa Wkly Report 10-16Feb: 1908 cholera cases w 24 deaths confirmed in Nampula, Niassa &amp; Tete Mozambique http:\/\/\u2026","26530":" &amp; colleagues on premptive use of cholera vaccines in high risk areas of Ebola countries http:\/\/t.co\/WYQpfxmMyx vaccineswork"}}