{"publish_date":{"2639":20151112,"2666":20151112,"2637":20151112},"url":{"2639":null,"2666":null,"2637":null},"topic":{"2639":"unkno","2666":"unkno","2637":"unkno"},"model1_prediction":{"2639":1,"2666":1,"2637":1},"model1_prediction_prob":{"2639":0.8175003871,"2666":0.6966644492,"2637":0.5712988421},"tweet_text":{"2639":"Lo biol\u00f3gico dan ganas de creer en algo sobrenatural... pero es solo un reflejo de la debilidad cognitiva de nuestra especie.","2666":"RT: The flu virus is constantly evolving. Stay protected and get the flu jab every year StayWellThisWinter https:\/\/t.co\/UkWWxD\u2026","2637":"RT: Este bulldog en patinete ha batido un r\u00e9cord, al pasar por debajo de las piernas de 30 personas. https:\/\/t.co\/JDmhcc5bKb"}}