{"publish_date":{"168481":20150121,"168454":20150121,"168309":20150121},"url":{"168481":null,"168454":null,"168309":null},"topic":{"168481":"unkno","168454":"unkno","168309":"unkno"},"model1_prediction":{"168481":1,"168454":1,"168309":1},"model1_prediction_prob":{"168481":0.641670943,"168454":0.5954069338,"168309":0.5050267319},"tweet_text":{"168481":" But there have probably been a lot more (thousands more) human H7N9 cases than human MERS cases.","168454":"RT: KSA reports 2 MERS cases &amp; 1 is already dead. Surveillance isn't A-1 if you only find cases after they die.  http:\/\/t\u2026","168309":"Lea el informe de la consulta de pa\u00eds para el que sucedi\u00f3 en el Per\u00fa en 2014 y acceda a otros materiales en : <a href=\"http:\/\/t.co\/XN5LNA0mWC\">http:\/\/t.co\/XN5LNA0mWC<\/a>"}}